{"kind":"books#volume","id":"W5rGGQAACAAJ","etag":"Dte9eIw7yC8","selfLink":"https://www.googleapis.com/books/v1/volumes/W5rGGQAACAAJ","volumeInfo":{"title":"Rolling Thunder","authors":["Doug Boyd"],"publisher":"Delta","publishedDate":"1974","description":"Records a southwestern Indian healer and spiritual leader's words on his knowledge of the Great Spirit and on the contemporary concerns of his people","industryIdentifiers":[{"type":"ISBN_10","identifier":"038528859X"},{"type":"ISBN_13","identifier":"9780385288590"}],"readingModes":{"text":false,"image":false},"pageCount":273,"printType":"BOOK","categories":["Juvenile Nonfiction"],"averageRating":2.5,"ratingsCount":2,"maturityRating":"NOT_MATURE","allowAnonLogging":false,"contentVersion":"preview-1.0.0","imageLinks":{"smallThumbnail":"http://books.google.com/books/content?id=W5rGGQAACAAJ&printsec=frontcover&img=1&zoom=5&source=gbs_api","thumbnail":"http://books.google.com/books/content?id=W5rGGQAACAAJ&printsec=frontcover&img=1&zoom=1&source=gbs_api"},"language":"en","previewLink":"http://books.google.com/books?id=W5rGGQAACAAJ&dq=Rolling+Thunder&hl=&cd=1&source=gbs_api","infoLink":"http://books.google.com/books?id=W5rGGQAACAAJ&dq=Rolling+Thunder&hl=&source=gbs_api","canonicalVolumeLink":"https://books.google.com/books/about/Rolling_Thunder.html?hl=&id=W5rGGQAACAAJ"},"saleInfo":{"country":"US","saleability":"NOT_FOR_SALE","isEbook":false},"accessInfo":{"country":"US","viewability":"NO_PAGES","embeddable":false,"publicDomain":false,"textToSpeechPermission":"ALLOWED","epub":{"isAvailable":false},"pdf":{"isAvailable":false},"webReaderLink":"http://play.google.com/books/reader?id=W5rGGQAACAAJ&hl=&printsec=frontcover&source=gbs_api","accessViewStatus":"NONE","quoteSharingAllowed":false},"searchInfo":{"textSnippet":"Records a southwestern Indian healer and spiritual leader&#39;s words on his knowledge of the Great Spirit and on the contemporary concerns of his people Rolling Thunder tells a story of tactics, innovations, breakthroughs, and battles, as ..."}}