{"kind":"books#volume","id":"yud-foXqGUEC","etag":"pPwNI+v8lfE","selfLink":"https://www.googleapis.com/books/v1/volumes/yud-foXqGUEC","volumeInfo":{"title":"Leviathan Wakes","authors":["James S. A. Corey"],"publisher":"Orbit","publishedDate":"2011-06-15","description":"The first book in the revolutionary NYT bestselling Expanse series, Leviathan Wakes introduces Captain James Holden, his crew, and Detective Miller as they unravel a horrifying solar system wide conspiracy that begins with a single missing girl. Now a Prime Original series. Leviathan Wakes is James S. A. Corey's first novel in the epic, New York Times bestselling series the Expanse, a modern masterwork of science fiction where humanity has colonized the solar system. Two hundred years after migrating into space, mankind is in turmoil. When a reluctant ship's captain and washed-up detective find themselves involved in the case of a missing girl, what they discover brings our solar system to the brink of civil war, and exposes the greatest conspiracy in human history. Leviathan Wakes is the breakneck science fiction adventure that launched the epic bestselling Expanse series. The ExpanseLeviathan WakesCaliban's WarAbaddon's GateCibola BurnNemesis GamesBabylon's AshesPersepolis RisingTiamat's Wrath The Expanse Short FictionThe Butcher of Anderson StationGods of RiskThe ChurnThe Vital Abyss","industryIdentifiers":[{"type":"ISBN_10","identifier":"0316134678"},{"type":"ISBN_13","identifier":"9780316134675"}],"readingModes":{"text":true,"image":false},"pageCount":592,"printType":"BOOK","categories":["Fiction"],"averageRating":4,"ratingsCount":167,"maturityRating":"NOT_MATURE","allowAnonLogging":true,"contentVersion":"2.26.25.0.preview.2","panelizationSummary":{"containsEpubBubbles":false,"containsImageBubbles":false},"imageLinks":{"smallThumbnail":"http://books.google.com/books/content?id=yud-foXqGUEC&printsec=frontcover&img=1&zoom=5&edge=curl&source=gbs_api","thumbnail":"http://books.google.com/books/content?id=yud-foXqGUEC&printsec=frontcover&img=1&zoom=1&edge=curl&source=gbs_api"},"language":"en","previewLink":"http://books.google.com/books?id=yud-foXqGUEC&printsec=frontcover&dq=Leviathan+Wakes&hl=&cd=1&source=gbs_api","infoLink":"https://play.google.com/store/books/details?id=yud-foXqGUEC&source=gbs_api","canonicalVolumeLink":"https://play.google.com/store/books/details?id=yud-foXqGUEC"},"saleInfo":{"country":"US","saleability":"FOR_SALE","isEbook":true,"listPrice":{"amount":9.99,"currencyCode":"USD"},"retailPrice":{"amount":9.99,"currencyCode":"USD"},"buyLink":"https://play.google.com/store/books/details?id=yud-foXqGUEC&rdid=book-yud-foXqGUEC&rdot=1&source=gbs_api","offers":[{"finskyOfferType":1,"listPrice":{"amountInMicros":9990000,"currencyCode":"USD"},"retailPrice":{"amountInMicros":9990000,"currencyCode":"USD"},"giftable":true}]},"accessInfo":{"country":"US","viewability":"PARTIAL","embeddable":false,"publicDomain":false,"textToSpeechPermission":"ALLOWED","epub":{"isAvailable":true,"acsTokenLink":"http://books.google.com/books/download/Leviathan_Wakes-sample-epub.acsm?id=yud-foXqGUEC&format=epub&output=acs4_fulfillment_token&dl_type=sample&source=gbs_api"},"pdf":{"isAvailable":false},"webReaderLink":"http://play.google.com/books/reader?id=yud-foXqGUEC&hl=&printsec=frontcover&source=gbs_api","accessViewStatus":"SAMPLE","quoteSharingAllowed":false},"searchInfo":{"textSnippet":"The first book in the revolutionary New York Times bestselling Expanse series, a modern masterwork of science fiction."}}