{"kind":"books#volume","id":"oHbvAAAACAAJ","etag":"Ih4A7Wht1T8","selfLink":"https://www.googleapis.com/books/v1/volumes/oHbvAAAACAAJ","volumeInfo":{"title":"Popbot","authors":["Ashley Wood","Sam Kieth"],"publisher":"Idea & Design Works Llc","publishedDate":"2003-06-01","description":"The second act of Popbot, the wonderfully warped epic from the mind of Ashley Wood, kicks off with the biggest fight in comic history! Kitty is missing, Popbot's gone dark, and, if Sam Kieth ain't looking, the Maxx may show up too!","industryIdentifiers":[{"type":"ISBN_10","identifier":"0971977593"},{"type":"ISBN_13","identifier":"9780971977594"}],"readingModes":{"text":false,"image":false},"pageCount":48,"printType":"BOOK","categories":["Comics & Graphic Novels"],"maturityRating":"NOT_MATURE","allowAnonLogging":false,"contentVersion":"preview-1.0.0","comicsContent":true,"imageLinks":{"smallThumbnail":"http://books.google.com/books/content?id=oHbvAAAACAAJ&printsec=frontcover&img=1&zoom=5&source=gbs_api","thumbnail":"http://books.google.com/books/content?id=oHbvAAAACAAJ&printsec=frontcover&img=1&zoom=1&source=gbs_api"},"language":"en","previewLink":"http://books.google.com/books?id=oHbvAAAACAAJ&dq=PopBot:+Book+4&hl=&cd=1&source=gbs_api","infoLink":"http://books.google.com/books?id=oHbvAAAACAAJ&dq=PopBot:+Book+4&hl=&source=gbs_api","canonicalVolumeLink":"https://books.google.com/books/about/Popbot.html?hl=&id=oHbvAAAACAAJ"},"saleInfo":{"country":"US","saleability":"NOT_FOR_SALE","isEbook":false},"accessInfo":{"country":"US","viewability":"NO_PAGES","embeddable":false,"publicDomain":false,"textToSpeechPermission":"ALLOWED","epub":{"isAvailable":false},"pdf":{"isAvailable":false},"webReaderLink":"http://play.google.com/books/reader?id=oHbvAAAACAAJ&hl=&printsec=frontcover&source=gbs_api","accessViewStatus":"NONE","quoteSharingAllowed":false},"searchInfo":{"textSnippet":"The second act of Popbot, the wonderfully warped epic from the mind of Ashley Wood, kicks off with the biggest fight in comic history! Kitty is missing, Popbot&#39;s gone dark, and, if Sam Kieth ain&#39;t looking, the Maxx may show up too!"}}