{"kind":"books#volume","id":"2xtZvYeNzVkC","etag":"ns8R5lJbQHc","selfLink":"https://www.googleapis.com/books/v1/volumes/2xtZvYeNzVkC","volumeInfo":{"title":"Writers of the Future","authors":["La Fayette Ron Hubbard"],"publisher":"Bridge Publications (CA)","publishedDate":"1989","industryIdentifiers":[{"type":"ISBN_10","identifier":"0884043797"},{"type":"ISBN_13","identifier":"9780884043799"}],"readingModes":{"text":false,"image":false},"pageCount":427,"printType":"BOOK","categories":["Fantasy fiction, American"],"averageRating":3.5,"ratingsCount":27,"maturityRating":"NOT_MATURE","allowAnonLogging":false,"contentVersion":"0.17.1.0.preview.0","panelizationSummary":{"containsEpubBubbles":false,"containsImageBubbles":false},"imageLinks":{"smallThumbnail":"http://books.google.com/books/content?id=2xtZvYeNzVkC&printsec=frontcover&img=1&zoom=5&source=gbs_api","thumbnail":"http://books.google.com/books/content?id=2xtZvYeNzVkC&printsec=frontcover&img=1&zoom=1&source=gbs_api"},"language":"en","previewLink":"http://books.google.com/books?id=2xtZvYeNzVkC&dq=L.+Ron+Hubbard+Presents:+The+Best+of+Writers+of+the+Future&hl=&cd=1&source=gbs_api","infoLink":"http://books.google.com/books?id=2xtZvYeNzVkC&dq=L.+Ron+Hubbard+Presents:+The+Best+of+Writers+of+the+Future&hl=&source=gbs_api","canonicalVolumeLink":"https://books.google.com/books/about/Writers_of_the_Future.html?hl=&id=2xtZvYeNzVkC"},"saleInfo":{"country":"US","saleability":"NOT_FOR_SALE","isEbook":false},"accessInfo":{"country":"US","viewability":"NO_PAGES","embeddable":false,"publicDomain":false,"textToSpeechPermission":"ALLOWED","epub":{"isAvailable":false},"pdf":{"isAvailable":false},"webReaderLink":"http://play.google.com/books/reader?id=2xtZvYeNzVkC&hl=&printsec=frontcover&source=gbs_api","accessViewStatus":"NONE","quoteSharingAllowed":false}}