{"kind":"books#volume","id":"cl8ie-5LxmEC","etag":"jYG/FQQHRv4","selfLink":"https://www.googleapis.com/books/v1/volumes/cl8ie-5LxmEC","volumeInfo":{"title":"Rocket Boys","subtitle":"A Memoir","authors":["Homer H. Hickam"],"publisher":"Random House Digital, Inc.","publishedDate":"2000","description":"The author traces the boyhood enthusiasm for rockets that eventually led to a career at NASA, describing how he built model rockets in the family garage in West Virginia, inspired by the launch of the Soviet satellite Sputnik. Reprint.","industryIdentifiers":[{"type":"ISBN_13","identifier":"9780385333214"},{"type":"ISBN_10","identifier":"0385333218"}],"readingModes":{"text":false,"image":false},"pageCount":368,"printType":"BOOK","categories":["Biography & Autobiography"],"averageRating":4,"ratingsCount":27,"maturityRating":"NOT_MATURE","allowAnonLogging":false,"contentVersion":"0.3.1.0.preview.0","panelizationSummary":{"containsEpubBubbles":false,"containsImageBubbles":false},"imageLinks":{"smallThumbnail":"http://books.google.com/books/content?id=cl8ie-5LxmEC&printsec=frontcover&img=1&zoom=5&edge=curl&source=gbs_api","thumbnail":"http://books.google.com/books/content?id=cl8ie-5LxmEC&printsec=frontcover&img=1&zoom=1&edge=curl&source=gbs_api"},"language":"en","previewLink":"http://books.google.com/books?id=cl8ie-5LxmEC&printsec=frontcover&dq=Rocket+Boys&hl=&cd=1&source=gbs_api","infoLink":"http://books.google.com/books?id=cl8ie-5LxmEC&dq=Rocket+Boys&hl=&source=gbs_api","canonicalVolumeLink":"https://books.google.com/books/about/Rocket_Boys.html?hl=&id=cl8ie-5LxmEC"},"saleInfo":{"country":"US","saleability":"NOT_FOR_SALE","isEbook":false},"accessInfo":{"country":"US","viewability":"PARTIAL","embeddable":true,"publicDomain":false,"textToSpeechPermission":"ALLOWED_FOR_ACCESSIBILITY","epub":{"isAvailable":false},"pdf":{"isAvailable":false},"webReaderLink":"http://play.google.com/books/reader?id=cl8ie-5LxmEC&hl=&printsec=frontcover&source=gbs_api","accessViewStatus":"SAMPLE","quoteSharingAllowed":false},"searchInfo":{"textSnippet":"The author traces the boyhood enthusiasm for rockets that eventually led to a career at NASA, describing how he built model rockets in the family garage in West Virginia, inspired by the launch of the Soviet satellite Sputnik. Reprint."}}